[
  {
    "id": "wee_tadpole",
    "name": "Wee Tadpole",
    "maxHp": 7,
    "attack": 7,
    "defense": 3,
    "speed": 7,
    "sides": 3,
    "attackRange": 0.16,
    "addAmount": 2,
    "attackType": "line",
    "attackDelayMs": 880,
    "travelTimeMs": 0,
    "movementType": "float",
    "icon": "tadpole",
    "fillColor": "#6ee7b7",
    "upgradeColorMod": "lighten"
  },
  {
    "id": "highland_sprog",
    "name": "Highland Sprog",
    "maxHp": 10,
    "attack": 14,
    "defense": 8,
    "speed": 9,
    "sides": 4,
    "attackRange": 0.055,
    "addAmount": 2,
    "attackType": "instant",
    "attackDelayMs": 820,
    "travelTimeMs": 0,
    "movementType": "hop",
    "icon": "frog",
    "fillColor": "#4ade80",
    "upgradeColorMod": "spectrum"
  },
  {
    "id": "bagpipe_croaker",
    "name": "Bagpipe Croaker",
    "maxHp": 13,
    "attack": 11,
    "defense": 6,
    "speed": 11,
    "sides": 5,
    "attackRange": 0.18,
    "addAmount": 1,
    "attackType": "line",
    "attackDelayMs": 760,
    "travelTimeMs": 0,
    "movementType": "float",
    "icon": "bagpipes",
    "fillColor": "#34d399",
    "upgradeColorMod": "saturate"
  },
  {
    "id": "laird_bullfrog",
    "name": "Laird Bullfrog",
    "maxHp": 18,
    "attack": 19,
    "defense": 14,
    "speed": 7,
    "sides": 6,
    "attackRange": 0.055,
    "addAmount": 1,
    "attackType": "instant",
    "attackDelayMs": 860,
    "travelTimeMs": 0,
    "movementType": "charge",
    "icon": "frog-prince",
    "fillColor": "#22c55e",
    "upgradeColorMod": "hue_shift"
  },
  {
    "id": "whisky_spitter",
    "name": "Whisky Spitter",
    "maxHp": 17,
    "attack": 13,
    "defense": 8,
    "speed": 12,
    "sides": 7,
    "attackRange": 0.18,
    "addAmount": 1,
    "attackType": "projectile",
    "attackDelayMs": 800,
    "travelTimeMs": 320,
    "movementType": "float",
    "icon": "whisky",
    "fillColor": "#84cc16",
    "upgradeColorMod": "saturate"
  },
  {
    "id": "caber_leaper",
    "name": "Caber Leaper",
    "maxHp": 20,
    "attack": 22,
    "defense": 13,
    "speed": 13,
    "sides": 8,
    "attackRange": 0.055,
    "addAmount": 1,
    "attackType": "instant",
    "attackDelayMs": 740,
    "travelTimeMs": 0,
    "movementType": "hop",
    "icon": "frog-foot",
    "fillColor": "#2dd4bf",
    "upgradeColorMod": "spectrum"
  },
  {
    "id": "cauldron_croaker",
    "name": "Cauldron Croaker",
    "maxHp": 22,
    "attack": 14,
    "defense": 9,
    "speed": 14,
    "sides": 9,
    "attackRange": 0.16,
    "addAmount": 2,
    "attackType": "line",
    "attackDelayMs": 720,
    "travelTimeMs": 0,
    "movementType": "float",
    "icon": "cauldron",
    "fillColor": "#5eead4",
    "upgradeColorMod": "lighten"
  },
  {
    "id": "thistle_brute",
    "name": "Thistle Brute",
    "maxHp": 28,
    "attack": 28,
    "defense": 22,
    "speed": 10,
    "sides": 10,
    "attackRange": 0.055,
    "addAmount": 1,
    "attackType": "instant",
    "attackDelayMs": 780,
    "travelTimeMs": 0,
    "movementType": "hop",
    "icon": "thistle",
    "fillColor": "#65a30d",
    "upgradeColorMod": "saturate"
  },
  {
    "id": "midgie_toad",
    "name": "Midgie Toad",
    "maxHp": 27,
    "attack": 17,
    "defense": 13,
    "speed": 14,
    "sides": 11,
    "attackRange": 0.17,
    "addAmount": 1,
    "attackType": "multi",
    "attackDelayMs": 700,
    "travelTimeMs": 0,
    "movementType": "float",
    "icon": "poison-gas",
    "fillColor": "#a3e635",
    "upgradeColorMod": "hue_shift"
  },
  {
    "id": "claymore_knight",
    "name": "Claymore Knight",
    "maxHp": 31,
    "attack": 33,
    "defense": 27,
    "speed": 11,
    "sides": 12,
    "attackRange": 0.055,
    "addAmount": 1,
    "attackType": "instant",
    "attackDelayMs": 760,
    "travelTimeMs": 0,
    "movementType": "charge",
    "icon": "claymore",
    "fillColor": "#16a34a",
    "upgradeColorMod": "lighten"
  },
  {
    "id": "nessie_seer",
    "name": "Nessie Seer",
    "maxHp": 30,
    "attack": 21,
    "defense": 15,
    "speed": 17,
    "sides": 13,
    "attackRange": 0.17,
    "addAmount": 1,
    "attackType": "line",
    "attackDelayMs": 640,
    "travelTimeMs": 0,
    "movementType": "float",
    "icon": "sea-serpent",
    "fillColor": "#2dd4bf",
    "upgradeColorMod": "spectrum"
  },
  {
    "id": "highland_chieftain",
    "name": "Highland Chieftain",
    "maxHp": 35,
    "attack": 39,
    "defense": 33,
    "speed": 14,
    "sides": 14,
    "attackRange": 0.055,
    "addAmount": 1,
    "attackType": "instant",
    "attackDelayMs": 720,
    "travelTimeMs": 0,
    "movementType": "charge",
    "icon": "celtic-knot",
    "fillColor": "#15803d",
    "upgradeColorMod": "saturate"
  }
]
